{
  "file": "proofnet-58.lean",
  "stem": "proofnet-58",
  "verdict": "faithful",
  "reasoning": "The Lean statement `H.Normal ↔ ⁅(⊤ : Subgroup G), H⁆ ≤ H` is a direct, faithful encoding of the informal claim \"H is normal iff [G, H] ≤ H\". In Mathlib, `⁅H₁, H₂⁆` is the subgroup generated by commutators ⁅g₁, g₂⁆ with g₁ ∈ H₁ and g₂ ∈ H₂ (see `Mathlib/GroupTheory/Commutator/Basic.lean`), and `(⊤ : Subgroup G)` represents all of G, so `⁅⊤, H⁆` is precisely [G, H]. `H.Normal` is Mathlib's standard normality predicate. The iff and the universal quantification over groups G (via `{G : Type*} [Group G]`) and subgroups H match the informal statement exactly. There are no added or omitted hypotheses, nor any changes in quantifier structure or types.",
  "duration_ms": 32803,
  "cost_usd": 0.21738525
}